COPYING.md
MANIFEST.in
README.md
setup.py
djungle/__init__.py
djungle/bootstrap/__init__.py
djungle/bootstrap/static/.DS_Store
djungle/bootstrap/static/djungle/.DS_Store
djungle/bootstrap/static/djungle/bootstrap/css/bootstrap-responsive.css
djungle/bootstrap/static/djungle/bootstrap/css/bootstrap-responsive.min.css
djungle/bootstrap/static/djungle/bootstrap/css/bootstrap.css
djungle/bootstrap/static/djungle/bootstrap/css/bootstrap.min.css
djungle/bootstrap/static/djungle/bootstrap/img/glyphicons-halflings-white.png
djungle/bootstrap/static/djungle/bootstrap/img/glyphicons-halflings.png
djungle/bootstrap/static/djungle/bootstrap/js/bootstrap.full.js
djungle/bootstrap/static/djungle/bootstrap/js/bootstrap.js
djungle_bootstrap.egg-info/PKG-INFO
djungle_bootstrap.egg-info/SOURCES.txt
djungle_bootstrap.egg-info/dependency_links.txt
djungle_bootstrap.egg-info/namespace_packages.txt
djungle_bootstrap.egg-info/not-zip-safe
djungle_bootstrap.egg-info/requires.txt
djungle_bootstrap.egg-info/top_level.txt